odoo8_addon_l10n_es_account_financial_report_xlsx-8.0.1.0.0.99.dev8-py3.6-nspkg.pth
odoo_addons/l10n_es_account_financial_report_xlsx/README.rst
odoo_addons/l10n_es_account_financial_report_xlsx/__init__.py
odoo_addons/l10n_es_account_financial_report_xlsx/__openerp__.py
odoo_addons/l10n_es_account_financial_report_xlsx/i18n/bg.po
odoo_addons/l10n_es_account_financial_report_xlsx/i18n/ca.po
odoo_addons/l10n_es_account_financial_report_xlsx/i18n/ca_ES.po
odoo_addons/l10n_es_account_financial_report_xlsx/i18n/cs.po
odoo_addons/l10n_es_account_financial_report_xlsx/i18n/en_US.po
odoo_addons/l10n_es_account_financial_report_xlsx/i18n/es.po
odoo_addons/l10n_es_account_financial_report_xlsx/i18n/es_CO.po
odoo_addons/l10n_es_account_financial_report_xlsx/i18n/es_CR.po
odoo_addons/l10n_es_account_financial_report_xlsx/i18n/eu.po
odoo_addons/l10n_es_account_financial_report_xlsx/i18n/fr.po
odoo_addons/l10n_es_account_financial_report_xlsx/i18n/gl.po
odoo_addons/l10n_es_account_financial_report_xlsx/i18n/hr.po
odoo_addons/l10n_es_account_financial_report_xlsx/i18n/l10n_es_account_financial_report_xlsx.pot
odoo_addons/l10n_es_account_financial_report_xlsx/i18n/nl.po
odoo_addons/l10n_es_account_financial_report_xlsx/i18n/pl.po
odoo_addons/l10n_es_account_financial_report_xlsx/i18n/pt.po
odoo_addons/l10n_es_account_financial_report_xlsx/i18n/pt_BR.po
odoo_addons/l10n_es_account_financial_report_xlsx/i18n/ru.po
odoo_addons/l10n_es_account_financial_report_xlsx/i18n/sl.po
odoo_addons/l10n_es_account_financial_report_xlsx/i18n/sv.po
odoo_addons/l10n_es_account_financial_report_xlsx/i18n/tr.po
odoo_addons/l10n_es_account_financial_report_xlsx/i18n/vi.po
odoo_addons/l10n_es_account_financial_report_xlsx/report/__init__.py
odoo_addons/l10n_es_account_financial_report_xlsx/report/journal_entries_report_xlsx.py
odoo_addons/l10n_es_account_financial_report_xlsx/report/l10n_es_reports.xml
odoo_addons/l10n_es_account_financial_report_xlsx/static/description/icon.png
odoo8_addon_l10n_es_account_financial_report_xlsx-8.0.1.0.0.99.dev8.dist-info/METADATA
odoo8_addon_l10n_es_account_financial_report_xlsx-8.0.1.0.0.99.dev8.dist-info/WHEEL
odoo8_addon_l10n_es_account_financial_report_xlsx-8.0.1.0.0.99.dev8.dist-info/namespace_packages.txt
odoo8_addon_l10n_es_account_financial_report_xlsx-8.0.1.0.0.99.dev8.dist-info/top_level.txt
odoo8_addon_l10n_es_account_financial_report_xlsx-8.0.1.0.0.99.dev8.dist-info/RECORD
