Metadata-Version: 2.1
Name: odoo8-addon-l10n-es-account-financial-report-xlsx
Version: 8.0.1.0.0.99.dev8
Summary: Informes financieros para España XLSX
Home-page: https://odoo-community.org/
Author: RGB Consulting SL,TecnativaOdoo Community Association (OCA)
Author-email: support@odoo-community.org
License: AGPL-3
Platform: UNKNOWN
Classifier: Programming Language :: Python
Classifier: Framework :: Odoo
Classifier: License :: OSI Approved :: GNU Affero General Public License v3
Requires-Python: ~=2.7
Requires-Dist: odoo8-addon-l10n-es-account-financial-report
Requires-Dist: odoo8-addon-report-xlsx
Requires-Dist: odoo (<9.0a,>=8.0a)
